NEXRAD_quickplot-0.6.4.dist-info/LICENSE.txt
NEXRAD_quickplot-0.6.4.dist-info/METADATA
NEXRAD_quickplot-0.6.4.dist-info/RECORD
NEXRAD_quickplot-0.6.4.dist-info/WHEEL
NEXRAD_quickplot-0.6.4.dist-info/entry_points.txt
NEXRAD_quickplot-0.6.4.dist-info/top_level.txt
nexrad_quickplot/__init__.py
nexrad_quickplot/plots.py
