Metadata-Version: 2.1
Name: NEXRAD-quickplot
Version: 0.6.4
Summary: easily download and plot NEXRAD weather radar reflectivity data
Home-page: https://github.com/scivision/nexrad-quick-plot
Author: Michael Hirsch, Ph.D.
License: UNKNOWN
Keywords: nexrad,weather radar
Platform: UNKNOWN
Classifier: Development Status :: 4 - Beta
Classifier: Environment :: Console
Classifier: Intended Audience :: Science/Research
Classifier: Operating System :: OS Independent
Classifier: Programming Language :: Python :: 3.6
Classifier: Programming Language :: Python :: 3.7
Classifier: Topic :: Scientific/Engineering :: Atmospheric Science
Requires-Python: >= 3.6
Provides-Extra: tests
Provides-Extra: plots
Requires-Dist: python-dateutil
Requires-Dist: numpy
Requires-Dist: imageio
Requires-Dist: xarray
Requires-Dist: cython
Requires-Dist: scikit-image
Provides-Extra: plots
Requires-Dist: cartopy; extra == 'plots'
Requires-Dist: matplotlib; extra == 'plots'
Requires-Dist: seaborn; extra == 'plots'
Provides-Extra: tests
Requires-Dist: pytest; extra == 'tests'
Requires-Dist: pytest-cov; extra == 'tests'
Requires-Dist: coveralls; extra == 'tests'
Requires-Dist: flake8; extra == 'tests'
Requires-Dist: mypy; extra == 'tests'
